ustcjwxt/__init__.py
ustcjwxt/course_select.py
ustcjwxt/log.py
ustcjwxt/request_info.py
ustcjwxt/score.py
ustcjwxt/session.py
ustcjwxt-0.2.0.dist-info/licenses/LICENSE
ustcjwxt-0.2.0.dist-info/METADATA
ustcjwxt-0.2.0.dist-info/WHEEL
ustcjwxt-0.2.0.dist-info/top_level.txt
ustcjwxt-0.2.0.dist-info/RECORD
