Metadata-Version: 2.4
Name: ustcjwxt
Version: 0.2.0
Summary: ustc jwxt api, for study only
Home-page: https://github.com/brealid/ustcjwxt-python-lib
Author: brealid
Author-email: brealid@mail.ustc.edu.cn
Classifier: Programming Language :: Python :: 3
Classifier: License :: OSI Approved :: MIT License
Classifier: Operating System :: OS Independent
Requires-Python: >=3.6
License-File: LICENSE
Requires-Dist: requests
Requires-Dist: pycryptodome
Dynamic: author
Dynamic: author-email
Dynamic: classifier
Dynamic: description
Dynamic: description-content-type
Dynamic: home-page
Dynamic: license-file
Dynamic: requires-dist
Dynamic: requires-python
Dynamic: summary
